FracGrad/__init__.py
FracGrad/operators.py
FracGrad/optimizers.py
FracGrad-0.1.2.dist-info/LICENSE
FracGrad-0.1.2.dist-info/METADATA
FracGrad-0.1.2.dist-info/WHEEL
FracGrad-0.1.2.dist-info/top_level.txt
FracGrad-0.1.2.dist-info/RECORD
