Metadata-Version: 2.1
Name: FracGrad
Version: 0.1.2
Summary: Fractional derivatives based gradient descent optimizers for PyTorch
Home-page: https://github.com/Mohammadakhavan75/FracGrad
Author: Mohammad Akhavan Anvari
Author-email: mohammad.akhavan75@gmail.com
Classifier: Programming Language :: Python :: 3
Classifier: License :: OSI Approved :: Apache Software License
Classifier: Operating System :: OS Independent
Requires-Python: >=3.6
License-File: LICENSE
Requires-Dist: torch
